<?xml version="1.0" encoding="utf-8"?>
<FormStatePersist xmlns:xsd="http://www.w3.org/2001/XMLSchema" xmlns:xsi="http://www.w3.org/2001/XMLSchema-instance">
  <Size>
    <Width>923</Width>
    <Height>475</Height>
  </Size>
  <Location>
    <X>176</X>
    <Y>163</Y>
  </Location>
  <DipToPixelConversionFactors>
    <WidthFactor>1</WidthFactor>
    <HeightFactor>1</HeightFactor>
  </DipToPixelConversionFactors>
  <SplitterLocations />
  <GroupExpansionStateList>
    <GroupExpansionState>
      <Name>DESACTIVAR CONEXIÓN A VAULT</Name>
      <Expanded>true</Expanded>
    </GroupExpansionState>
    <GroupExpansionState>
      <Name>Grupo 1</Name>
      <Expanded>true</Expanded>
    </GroupExpansionState>
    <GroupExpansionState>
      <Name>VAULT</Name>
      <Expanded>true</Expanded>
    </GroupExpansionState>
  </GroupExpansionStateList>
  <TabGroupSelectedPageList />
</FormStatePersist>